CHANGES.txt
CREDITS.txt
INSTALL.bat
LICENSE.txt
README.txt
ez_setup.py
setup.py
tnef.py
version.txt
lib/strip.py
lib/tneflib.py
pytnef.egg-info/PKG-INFO
pytnef.egg-info/SOURCES.txt
pytnef.egg-info/top_level.txt
test/README.txt
test/body.tnef
test/data-before-name.tnef
test/multi-name-property.tnef
test/tests.py
test/two-files.tnef
