Metadata-Version: 1.0
Name: pytnef
Version: 0.2
Summary: pytnef library: wrapper to access MS TNEF-coded files (winmail.dat)
Home-page: UNKNOWN
Author: Petri Savolainen
Author-email: petri.savolainen@iki.fi
License: http://www.fsf.org/licensing/licenses/lgpl.txt
Platform: unix
Classifier: Development Status :: 3 - Alpha
Classifier: Intended Audience :: Developers
Classifier: License :: OSI Approved :: GNU Library or Lesser General Public License (LGPL)
Classifier: Programming Language :: Python
Classifier: Topic :: Software Development :: Libraries :: Python Modules
Classifier: Topic :: Software Development :: Libraries
Classifier: Topic :: Communications :: Email
Classifier: Operating System :: Unix
Classifier: Operating System :: POSIX
